gideonai/KnowledgeControl.py
gideonai/LogicControl.py
gideonai/MiscControl.py
gideonai/RequestControl.py
gideonai/SpeechControl.py
gideonai/__init__.py
gideonai/__main__.py
gideonai/exec.py
gideonai/playsong.py
gideonai/test.py
gideonai-6.9.6.9.dist-info/DESCRIPTION.rst
gideonai-6.9.6.9.dist-info/METADATA
gideonai-6.9.6.9.dist-info/RECORD
gideonai-6.9.6.9.dist-info/WHEEL
gideonai-6.9.6.9.dist-info/entry_points.txt
gideonai-6.9.6.9.dist-info/metadata.json
gideonai-6.9.6.9.dist-info/top_level.txt
